{
  "assetAdministrationShells": [
    {
      "assetInformation": {
        "assetKind": "Instance",
        "specificAssetId": {
          "externalSubjectId": {
            "keys": [
              {
                "type": "GlobalReference",
                "value": "something_random_ecd20100"
              }
            ],
            "type": "GlobalReference"
          },
          "name": "something_random_73ff3355",
          "value": "something_random_d43e0a3b"
        }
      },
      "id": "something_random_428f0205",
      "modelType": "AssetAdministrationShell"
    }
  ]
}